src/grumps/CHANGELOG.md
src/grumps/LICENSE
src/grumps/README.md
src/grumps/__about__.py
src/grumps/__init__.py
src/grumps/api/__init__.py
src/grumps/api/pipeLine.py
src/grumps/core/__init__.py
src/grumps/core/argParse.py
src/grumps/core/cleaners.py
src/grumps/core/cli.py
src/grumps/core/clique.py
src/grumps/core/distmat_converter.py
src/grumps/core/grumpsObj.py
src/grumps/core/shared.py
src/grumps/core/summary.py
src/grumps/modes/__init__.py
src/grumps/modes/modes.py
testgrumps-1.0.0.dist-info/METADATA
testgrumps-1.0.0.dist-info/WHEEL
testgrumps-1.0.0.dist-info/entry_points.txt
testgrumps-1.0.0.dist-info/licenses/LICENSE
testgrumps-1.0.0.dist-info/RECORD
