Metadata-Version: 2.3
Name: testgrumps
Version: 1.0.0
Summary: Genomic distance based Rapid Uncovering of Microbial Population Structures
Project-URL: Homepage, https://github.com/kalebabram/grumps
Project-URL: News, https://github.com/kalebabram/grumps/blob/master/CHANGELOG.md
Project-URL: Readme, https://github.com/kalebabram/grumps/blob/master/README.md
Project-URL: Issues, https://github.com/kalebabram/GRUMPS/issues
Author-email: Kaleb Abram <abram.kaleb@gmail.com>
Maintainer-email: Kaleb Abram <abram.kaleb@gmail.com>
License:                                  Apache License
License-File: LICENSE
Keywords: ANI,clustering,data cleaning,genome,machine learning,mash,population structure
Classifier: Development Status :: 4 - Beta
Classifier: Framework :: Hatch
Classifier: Intended Audience :: Developers
Classifier: Intended Audience :: Science/Research
Classifier: License :: OSI Approved :: Apache Software License
Classifier: Operating System :: MacOS :: MacOS X
Classifier: Operating System :: POSIX :: Linux
Classifier: Programming Language :: Python
Classifier: Programming Language :: Python :: 3
Classifier: Topic :: Scientific/Engineering :: Bio-Informatics
Requires-Python: >=3.7
Requires-Dist: networkx
Requires-Dist: numpy
Requires-Dist: pandas
Requires-Dist: scikit-learn
Requires-Dist: scipy
Requires-Dist: seaborn
